[
  {
    "label": "Home",
    "href": "/",
    "sublinks": []
  },
  {
    "label": "About Us",
    "href": "/about",
    "sublinks": [
      { "name": "Our Story", "href": "/about#story" },
      { "name": "Team", "href": "/about#team" },
      { "name": "Vision", "href": "/about#vision" }
    ]
  },
  {
    "label": "Services",
    "href": "/services",
    "sublinks": [
      { "name": "Coworking Consulting", "href": "/services/consulting" },
      { "name": "Space Design", "href": "/services/design" },
      { "name": "Marketing", "href": "/services/marketing" }
    ]
  },
  {
    "label": "Resources",
    "href": "/resources",
    "sublinks": [
      { "name": "Blog", "href": "/blog" },
      { "name": "Guides", "href": "/guides" },
      { "name": "Case Studies", "href": "/case-studies" }
    ]
  },
  {
    "label": "Contact",
    "href": "/contact",
    "sublinks": []
  }
]
